lit/BooleanExpression.py
lit/LitConfig.py
lit/LitTestCase.py
lit/ProgressBar.py
lit/ShCommands.py
lit/ShUtil.py
lit/Test.py
lit/TestRunner.py
lit/TestTimes.py
lit/TestingConfig.py
lit/__init__.py
lit/cl_arguments.py
lit/discovery.py
lit/display.py
lit/main.py
lit/reports.py
lit/run.py
lit/util.py
lit/worker.py
lit/builtin_commands/__init__.py
lit/builtin_commands/cat.py
lit/builtin_commands/diff.py
lit/formats/__init__.py
lit/formats/base.py
lit/formats/googletest.py
lit/formats/shtest.py
lit/llvm/__init__.py
lit/llvm/config.py
lit/llvm/subst.py
lit-18.1.7.dist-info/LICENSE.TXT
lit-18.1.7.dist-info/METADATA
lit-18.1.7.dist-info/WHEEL
lit-18.1.7.dist-info/entry_points.txt
lit-18.1.7.dist-info/top_level.txt
lit-18.1.7.dist-info/RECORD
