Metadata-Version: 2.1
Name: lit
Version: 18.1.7
Summary: A Software Testing Tool
Home-page: http://llvm.org
Author: Daniel Dunbar
Author-email: daniel@minormatter.com
License: Apache-2.0 with LLVM exception
Keywords: test C++ automatic discovery
Classifier: Development Status :: 3 - Alpha
Classifier: Environment :: Console
Classifier: Intended Audience :: Developers
Classifier: License :: OSI Approved :: Apache Software License
Classifier: Natural Language :: English
Classifier: Operating System :: OS Independent
Classifier: Programming Language :: Python
Classifier: Topic :: Software Development :: Testing
License-File: LICENSE.TXT
